cems_nuclei-3.2.0.dist-info/licenses/LICENSE.txt
nuclei/__init__.py
nuclei/_version.py
nuclei/api/__init__.py
nuclei/api/main.py
nuclei/client/__init__.py
nuclei/client/main.py
nuclei/client/utils.py
cems_nuclei-3.2.0.dist-info/METADATA
cems_nuclei-3.2.0.dist-info/WHEEL
cems_nuclei-3.2.0.dist-info/top_level.txt
cems_nuclei-3.2.0.dist-info/RECORD
