Metadata-Version: 2.4
Name: cems-nuclei
Version: 3.2.0
Summary: Python wrapper around NUCLEI's functionality.
License: MIT License
Project-URL: repository, https://github.com/cemsbv/nuclei
Keywords: API
Requires-Python: >=3.11
License-File: LICENSE.txt
Requires-Dist: requests<3,>=2.25.1
Requires-Dist: pyjwt<3,>=2.6.0
Provides-Extra: client
Requires-Dist: orjson<4,>=3; extra == "client"
Provides-Extra: test
Requires-Dist: coveralls; extra == "test"
Requires-Dist: pytest; extra == "test"
Provides-Extra: docs
Requires-Dist: Sphinx==8.2.3; extra == "docs"
Requires-Dist: sphinx-autodoc-typehints==3.2.0; extra == "docs"
Requires-Dist: sphinx_rtd_theme; extra == "docs"
Requires-Dist: asteroid-sphinx-theme==0.0.3; extra == "docs"
Requires-Dist: anywidget==0.9.18; extra == "docs"
Requires-Dist: numpy<3,>=2.2.4; extra == "docs"
Requires-Dist: ipython<10,>=9.1.0; extra == "docs"
Provides-Extra: lint
Requires-Dist: black; extra == "lint"
Requires-Dist: isort; extra == "lint"
Dynamic: license-file
